maieutics/Socrates.py
maieutics/__init__.py
maieutics/albert copy.py
maieutics/albert.py
maieutics/albert_past.py
maieutics/bm25_retreiver.py
maieutics/context_builder.py
maieutics/roberta.py
maieutics/utils.py
maieutics-0.13.dist-info/LICENSE
maieutics-0.13.dist-info/METADATA
maieutics-0.13.dist-info/WHEEL
maieutics-0.13.dist-info/top_level.txt
maieutics-0.13.dist-info/RECORD
