Metadata-Version: 2.1
Name: maieutics
Version: 0.13
Summary: Maieutics
Author: Alfredo Lozano
Author-email: lozanoa94@gmail.com
License: UNKNOWN
Platform: UNKNOWN
License-File: LICENSE
Requires-Dist: bs4 (==0.0.1)
Requires-Dist: google (==2.0.3)
Requires-Dist: nltk (==3.4.5)
Requires-Dist: rank-bm25 (==0.2)
Requires-Dist: torch (==1.10.2)
Requires-Dist: transformers (==4.16.2)
